funapi/__init__.py
funcode-0.0.1.dist-info/LICENSE
funcode-0.0.1.dist-info/METADATA
funcode-0.0.1.dist-info/WHEEL
funcode-0.0.1.dist-info/entry_points.txt
funcode-0.0.1.dist-info/top_level.txt
funcode-0.0.1.dist-info/RECORD
